{
  "testName": "busyTimeout2000ConcurrentWrites",
  "timestamp": "2025-12-24T18:28:35.781Z",
  "configurations": [
    {
      "concurrency": 1,
      "totalWrites": 100000,
      "metrics": {
        "total": 100000,
        "successful": 100000,
        "errors": 0,
        "lockErrors": 0,
        "successRate": 100,
        "avgTime": 0.9914040975899707,
        "p95": 1.4464020000013988,
        "p99": 1.948259999990114,
        "writesPerSec": 770.4978591775116,
        "totalDuration": 129786.21395100001
      }
    },
    {
      "concurrency": 2,
      "totalWrites": 100000,
      "metrics": {
        "total": 100000,
        "successful": 100000,
        "errors": 0,
        "lockErrors": 0,
        "successRate": 100,
        "avgTime": 1.6886288524899862,
        "p95": 2.762040999979945,
        "p99": 4.9837010000192095,
        "writesPerSec": 728.7795271186969,
        "totalDuration": 137215.709661
      }
    },
    {
      "concurrency": 4,
      "totalWrites": 100000,
      "metrics": {
        "total": 100000,
        "successful": 100000,
        "errors": 0,
        "lockErrors": 0,
        "successRate": 100,
        "avgTime": 5.1784702237599785,
        "p95": 11.082767000014428,
        "p99": 22.131762000033632,
        "writesPerSec": 325.7045606179658,
        "totalDuration": 307026.71098699997
      }
    },
    {
      "concurrency": 8,
      "totalWrites": 100000,
      "metrics": {
        "total": 100000,
        "successful": 100000,
        "errors": 0,
        "lockErrors": 0,
        "successRate": 100,
        "avgTime": 24.41551083527973,
        "p95": 64.87026599992532,
        "p99": 92.52703699993435,
        "writesPerSec": 118.90622514241731,
        "totalDuration": 840998.8617519999
      }
    },
    {
      "concurrency": 16,
      "totalWrites": 100000,
      "metrics": {
        "total": 100000,
        "successful": 100000,
        "errors": 0,
        "lockErrors": 0,
        "successRate": 100,
        "avgTime": 70.76847621396917,
        "p95": 194.48038200009614,
        "p99": 289.97224400006235,
        "writesPerSec": 83.61320253801371,
        "totalDuration": 1195983.373015
      }
    },
    {
      "concurrency": 32,
      "totalWrites": 100000,
      "metrics": {
        "total": 100000,
        "successful": 100000,
        "errors": 0,
        "lockErrors": 0,
        "successRate": 100,
        "avgTime": 120.32096336830992,
        "p95": 360.3907139999792,
        "p99": 666.2254380001687,
        "writesPerSec": 75.49499055500947,
        "totalDuration": 1324591.198235
      }
    },
    {
      "concurrency": 64,
      "totalWrites": 100000,
      "metrics": {
        "total": 100000,
        "successful": 99646,
        "errors": 354,
        "lockErrors": 354,
        "successRate": 99.646,
        "avgTime": 319.02718977884905,
        "p95": 1182.743586000055,
        "p99": 1714.531336999964,
        "writesPerSec": 48.93447643132562,
        "totalDuration": 2036314.8288679998
      }
    },
    {
      "concurrency": 128,
      "totalWrites": 100000,
      "metrics": {
        "total": 100000,
        "successful": 98149,
        "errors": 1851,
        "lockErrors": 1851,
        "successRate": 98.149,
        "avgTime": 580.2356389403649,
        "p95": 1634.2089550001547,
        "p99": 2002.8102350002155,
        "writesPerSec": 68.09951381166208,
        "totalDuration": 1441258.4540830003
      }
    }
  ]
}